{
    "key": "PLACEHOLDER",
    "playback_status": "PLACEHOLDER",
    "user": "PLACEHOLDER",
    "media": {
        "type": "{media_type}",
        "playback": {
            "year": "{year}",
            "studio": "{studio}",
            "content_raiting": "{content_rating}",
            "raiting": "{rating}",
            "name": "{show_name}",
            "season": "{season_name}",
            "episode": "{episode_name}",
            "summary": "{summary}",
            "season_number": "{season_num}",
            "episode_number": "{episode_num}",
            "poster_url": "{poster_url}"
        },
        "time": "{time}",
        "ID": "{themoviedb_id}"
    }
}